pyarchops_helpers/__init__.py
pyarchops_helpers/helpers.py
pyarchops_helpers-0.0.8.dist-info/AUTHORS.rst
pyarchops_helpers-0.0.8.dist-info/LICENSE
pyarchops_helpers-0.0.8.dist-info/METADATA
pyarchops_helpers-0.0.8.dist-info/WHEEL
pyarchops_helpers-0.0.8.dist-info/top_level.txt
pyarchops_helpers-0.0.8.dist-info/RECORD
