Metadata-Version: 2.1
Name: pyarchops-helpers
Version: 0.0.8
Summary: Install All helpers
Home-page: https://github.com/pyarchops/helpers
Author: Azul
Author-email: pyarchops@azulinho.com
License: MIT license
Keywords: pyarchops_helpers
Platform: UNKNOWN
Classifier: Development Status :: 2 - Pre-Alpha
Classifier: Intended Audience :: Developers
Classifier: License :: OSI Approved :: MIT License
Classifier: Natural Language :: English
Classifier: Programming Language :: Python :: 3.7
Requires-Dist: suitable
